{"cameraMode":{"drawMode":0,"name":"Shaded","section":"Shading Mode"},"sceneLighting":true,"audioPlay":false,"sceneViewState":{"m_AlwaysRefresh":false,"showFog":true,"showSkybox":true,"showFlares":true,"showImageEffects":true,"showParticleSystems":true,"showVisualEffectGraphs":true,"m_FxEnabled":true},"in2DMode":false,"pivot":{"x":0.5446369051933289,"y":-0.23909536004066468,"z":-12.608489990234375},"rotation":{"x":0.10208909213542938,"y":0.8399730920791626,"z":-0.16987329721450807,"w":0.5052466988563538},"size":1.571008563041687,"orthographic":false}